<pdfxml ModDate="D:20081203142806-06'00'" CreationDate="D:20070322154219+01'00'" Title=" " Creator="Acrobat PDFMaker 6.0 for Word" Author="armando cceres estrada" Producer="Acrobat Distiller 6.0 (Windows)" SourceModified="D:20061205142346">
  <LTPage y0="0" y1="792" x0="0" x1="612" width="612" height="792" bbox="[0, 0, 612, 792]" pageid="1" rotate="0" page_index="64" page_label="">
    <LTTextLineHorizontal y0="749.266" y1="759.286" x0="222.66" x1="391.745" width="169.085" height="10.02" bbox="[222.66, 749.266, 391.745, 759.286]" word_margin="0.1"><LTTextBoxHorizontal y0="749.266" y1="759.286" x0="222.66" x1="391.745" width="169.085" height="10.02" bbox="[222.66, 749.266, 391.745, 759.286]" index="0">Vadem&#233;cum Nacional de Plantas Medicinales </LTTextBoxHorizontal></LTTextLineHorizontal>
    <LTTextLineHorizontal y0="688.056" y1="712.056" x0="388.98" x1="491.748" width="102.768" height="24.0" bbox="[388.98, 688.056, 491.748, 712.056]" word_margin="0.1"><LTTextBoxHorizontal y0="688.056" y1="712.056" x0="388.98" x1="491.748" width="102.768" height="24.0" bbox="[388.98, 688.056, 491.748, 712.056]" index="1">BORRAJA </LTTextBoxHorizontal></LTTextLineHorizontal>
    <LTTextBoxHorizontal y0="663.886" y1="686.483" x0="351.0" x1="526.455" width="175.455" height="22.597" bbox="[351.0, 663.886, 526.455, 686.483]" index="2"><LTTextLineHorizontal y0="675.503" y1="686.483" x0="361.2" x1="516.58" width="155.38" height="10.98" bbox="[361.2, 675.503, 516.58, 686.483]" word_margin="0.1">Borago officinalis L. (Boraginaceae) </LTTextLineHorizontal><LTTextLineHorizontal y0="663.886" y1="673.906" x0="351.0" x1="526.455" width="175.455" height="10.02" bbox="[351.0, 663.886, 526.455, 673.906]" word_margin="0.1">Dibujo seg&#250;n Severa en Vol&#225;k &amp; Stodola, 1984. </LTTextLineHorizontal></LTTextBoxHorizontal>
    <LTTextLineHorizontal y0="630.743" y1="641.723" x0="487.56" x1="543.655" width="56.095" height="10.98" bbox="[487.56, 630.743, 543.655, 641.723]" word_margin="0.1"><LTTextBoxHorizontal y0="630.743" y1="641.723" x0="487.56" x1="543.655" width="56.095" height="10.98" bbox="[487.56, 630.743, 543.655, 641.723]" index="3">SINONIMIAS </LTTextBoxHorizontal></LTTextLineHorizontal>
    <LTTextLineHorizontal y0="581.543" y1="592.523" x0="401.94" x1="543.664" width="141.724" height="10.98" bbox="[401.94, 581.543, 543.664, 592.523]" word_margin="0.1"><LTTextBoxHorizontal y0="581.543" y1="592.523" x0="401.94" x1="543.664" width="141.724" height="10.98" bbox="[401.94, 581.543, 543.664, 592.523]" index="4">OTROS NOMBRES POPULARES </LTTextBoxHorizontal></LTTextLineHorizontal>
    <LTTextLineHorizontal y0="532.282" y1="543.262" x0="379.86" x1="543.691" width="163.831" height="10.98" bbox="[379.86, 532.282, 543.691, 543.262]" word_margin="0.1"><LTTextBoxHorizontal y0="532.282" y1="543.262" x0="379.86" x1="543.691" width="163.831" height="10.98" bbox="[379.86, 532.282, 543.691, 543.262]" index="5">PARTES USADAS MEDICINALMENTE </LTTextBoxHorizontal></LTTextLineHorizontal>
    <LTTextLineHorizontal y0="513.682" y1="524.662" x0="474.54" x1="543.641" width="69.101" height="10.98" bbox="[474.54, 513.682, 543.641, 524.662]" word_margin="0.1"><LTTextBoxHorizontal y0="513.682" y1="524.662" x0="474.54" x1="543.641" width="69.101" height="10.98" bbox="[474.54, 513.682, 543.641, 524.662]" index="6">Hojas y Semillas </LTTextBoxHorizontal></LTTextLineHorizontal>
    <LTTextBoxHorizontal y0="419.303" y1="493.403" x0="320.22" x1="543.698" width="223.478" height="74.099" bbox="[320.22, 419.303, 543.698, 493.403]" index="7"><LTTextLineHorizontal y0="482.423" y1="493.403" x0="320.22" x1="543.698" width="223.478" height="10.98" bbox="[320.22, 482.423, 543.698, 493.403]" word_margin="0.1">refieren su propiedad diur&#233;tica. Los celtas preparaban </LTTextLineHorizontal><LTTextLineHorizontal y0="469.763" y1="480.743" x0="320.22" x1="543.595" width="223.375" height="10.98" bbox="[320.22, 469.763, 543.595, 480.743]" word_margin="0.1">un vino que les daba coraje para la batalla. Mattioli y </LTTextLineHorizontal><LTTextLineHorizontal y0="457.163" y1="468.143" x0="320.22" x1="543.683" width="223.463" height="10.98" bbox="[320.22, 457.163, 543.683, 468.143]" word_margin="0.1">Laguna refieren su uso por Diosc&#243;rides, aunque Font </LTTextLineHorizontal><LTTextLineHorizontal y0="444.564" y1="455.544" x0="320.22" x1="543.688" width="223.468" height="10.98" bbox="[320.22, 444.564, 543.688, 455.544]" word_margin="0.1">Quer asegura que &#233;ste no la conoci&#243; y que su origen </LTTextLineHorizontal><LTTextLineHorizontal y0="431.904" y1="442.884" x0="320.22" x1="543.608" width="223.389" height="10.98" bbox="[320.22, 431.904, 543.608, 442.884]" word_margin="0.1">es atl&#225;ntico hispano-marroqu&#237; y no de Siria como se </LTTextLineHorizontal><LTTextLineHorizontal y0="419.303" y1="430.284" x0="320.22" x1="522.163" width="201.943" height="10.981" bbox="[320.22, 419.303, 522.163, 430.284]" word_margin="0.1">cre&#237;a 5. Introducida en Am&#233;rica en el siglo XVII 6. </LTTextLineHorizontal></LTTextBoxHorizontal>
    <LTTextBoxHorizontal y0="375.443" y1="411.683" x0="320.22" x1="543.571" width="223.351" height="36.24" bbox="[320.22, 375.443, 543.571, 411.683]" index="8"><LTTextLineHorizontal y0="400.703" y1="411.683" x0="320.22" x1="543.571" width="223.351" height="10.98" bbox="[320.22, 400.703, 543.571, 411.683]" word_margin="0.1">La infusi&#243;n y decocci&#243;n se usan para tratar afecciones </LTTextLineHorizontal><LTTextLineHorizontal y0="388.043" y1="399.023" x0="320.22" x1="541.069" width="220.849" height="10.98" bbox="[320.22, 388.043, 541.069, 399.023]" word_margin="0.1">respiratorias, litiasis, inflamaci&#243;n y enfermedad hep&#225;- </LTTextLineHorizontal><LTTextLineHorizontal y0="375.443" y1="386.424" x0="320.22" x1="536.623" width="216.403" height="10.98" bbox="[320.22, 375.443, 536.623, 386.424]" word_margin="0.1">tica 7. T&#243;picamente se usa para madurar abscesos 4. </LTTextLineHorizontal></LTTextBoxHorizontal>
    <LTTextBoxHorizontal y0="318.923" y1="367.823" x0="320.22" x1="543.626" width="223.406" height="48.9" bbox="[320.22, 318.923, 543.626, 367.823]" index="9"><LTTextLineHorizontal y0="356.843" y1="367.823" x0="320.22" x1="543.609" width="223.389" height="10.98" bbox="[320.22, 356.843, 543.609, 367.823]" word_margin="0.1">A las hojas se les atribuye propiedad depurativa, </LTTextLineHorizontal><LTTextLineHorizontal y0="344.183" y1="355.163" x0="320.22" x1="540.964" width="220.744" height="10.98" bbox="[320.22, 344.183, 540.964, 355.163]" word_margin="0.1">sudor&#237;fica, diur&#233;tica, emoliente, expectorante, galacto- </LTTextLineHorizontal><LTTextLineHorizontal y0="331.583" y1="342.564" x0="320.22" x1="543.626" width="223.406" height="10.98" bbox="[320.22, 331.583, 543.626, 342.564]" word_margin="0.1">goga, pectoral y t&#243;nica 3. Las hojas tiernas cocidas se </LTTextLineHorizontal><LTTextLineHorizontal y0="318.923" y1="329.903" x0="320.22" x1="469.11" width="148.89" height="10.98" bbox="[320.22, 318.923, 469.11, 329.903]" word_margin="0.1">consumen como hierba alimenticia. </LTTextLineHorizontal></LTTextBoxHorizontal>
    <LTTextBoxHorizontal y0="287.724" y1="311.303" x0="320.22" x1="543.556" width="223.336" height="23.58" bbox="[320.22, 287.724, 543.556, 311.303]" index="10"><LTTextLineHorizontal y0="300.323" y1="311.303" x0="320.22" x1="543.556" width="223.336" height="10.98" bbox="[320.22, 300.323, 543.556, 311.303]" word_margin="0.1">Las semillas se usan como fuente de un complemento </LTTextLineHorizontal><LTTextLineHorizontal y0="287.724" y1="298.704" x0="320.22" x1="537.828" width="217.608" height="10.98" bbox="[320.22, 287.724, 537.828, 298.704]" word_margin="0.1">nutricional, se les atribuye propiedad hipolipemiante. </LTTextLineHorizontal></LTTextBoxHorizontal>
    <LTTextLineHorizontal y0="257.064" y1="268.044" x0="320.22" x1="518.099" width="197.88" height="10.98" bbox="[320.22, 257.064, 518.099, 268.044]" word_margin="0.1"><LTTextBoxHorizontal y0="257.064" y1="268.044" x0="320.22" x1="518.099" width="197.88" height="10.98" bbox="[320.22, 257.064, 518.099, 268.044]" index="11">FARMACOLOG&#205;A EXPERIMENTAL Y CL&#205;NICA </LTTextBoxHorizontal></LTTextLineHorizontal>
    <LTTextBoxHorizontal y0="225.863" y1="249.444" x0="320.22" x1="543.643" width="223.423" height="23.581" bbox="[320.22, 225.863, 543.643, 249.444]" index="12"><LTTextLineHorizontal y0="238.464" y1="249.444" x0="320.22" x1="543.643" width="223.423" height="10.98" bbox="[320.22, 238.464, 543.643, 249.444]" word_margin="0.1">El extracto de hojas es activo contra S. pyogenes e </LTTextLineHorizontal><LTTextLineHorizontal y0="225.863" y1="236.844" x0="320.22" x1="505.423" width="185.203" height="10.981" bbox="[320.22, 225.863, 505.423, 236.844]" word_margin="0.1">inactivo contra S. aureus y S. pneumoniae 8. </LTTextLineHorizontal></LTTextBoxHorizontal>
    <LTTextBoxHorizontal y0="106.223" y1="218.183" x0="320.22" x1="543.63" width="223.41" height="111.96" bbox="[320.22, 106.223, 543.63, 218.183]" index="13"><LTTextLineHorizontal y0="207.203" y1="218.183" x0="320.22" x1="543.63" width="223.409" height="10.98" bbox="[320.22, 207.203, 543.63, 218.183]" word_margin="0.1">La infusi&#243;n de las hojas aumenta moderadamente el </LTTextLineHorizontal><LTTextLineHorizontal y0="194.603" y1="205.583" x0="320.22" x1="543.593" width="223.373" height="10.98" bbox="[320.22, 194.603, 543.593, 205.583]" word_margin="0.1">volumen urinario en ratas 9. Tiene efecto expectorante </LTTextLineHorizontal><LTTextLineHorizontal y0="182.004" y1="192.984" x0="320.22" x1="541.127" width="220.907" height="10.98" bbox="[320.22, 182.004, 541.127, 192.984]" word_margin="0.1">asociado a una acci&#243;n antiinflamatoria sobre la muco- </LTTextLineHorizontal><LTTextLineHorizontal y0="169.344" y1="180.324" x0="320.22" x1="543.617" width="223.397" height="10.98" bbox="[320.22, 169.344, 543.617, 180.324]" word_margin="0.1">sa bronquial. El extracto etan&#243;lico de las semillas </LTTextLineHorizontal><LTTextLineHorizontal y0="156.744" y1="167.724" x0="320.22" x1="541.076" width="220.856" height="10.98" bbox="[320.22, 156.744, 541.076, 167.724]" word_margin="0.1">desgrasadas tiene actividad antioxidante y neutraliza- </LTTextLineHorizontal><LTTextLineHorizontal y0="144.083" y1="155.064" x0="320.22" x1="541.145" width="220.925" height="10.981" bbox="[320.22, 144.083, 541.145, 155.064]" word_margin="0.1">dor de radicales libres 10. En 138 pacientes con afec- </LTTextLineHorizontal><LTTextLineHorizontal y0="131.484" y1="142.464" x0="320.22" x1="543.594" width="223.375" height="10.98" bbox="[320.22, 131.484, 543.594, 142.464]" word_margin="0.1">ci&#243;n bronquial aguda fue expectorante y sedante de la </LTTextLineHorizontal><LTTextLineHorizontal y0="118.884" y1="129.864" x0="320.22" x1="543.61" width="223.391" height="10.98" bbox="[320.22, 118.884, 543.61, 129.864]" word_margin="0.1">tos, con resultados excelentes (49%) o buenos (42%) </LTTextLineHorizontal><LTTextLineHorizontal y0="106.223" y1="117.204" x0="320.22" x1="474.583" width="154.364" height="10.981" bbox="[320.22, 106.223, 474.583, 117.204]" word_margin="0.1">en la evoluci&#243;n de la enfermedad 11. </LTTextLineHorizontal></LTTextBoxHorizontal>
    <LTTextLineHorizontal y0="81.624" y1="92.604" x0="320.22" x1="535.119" width="214.899" height="10.98" bbox="[320.22, 81.624, 535.119, 92.604]" word_margin="0.1"><LTTextBoxHorizontal y0="81.624" y1="92.604" x0="320.22" x1="535.119" width="214.899" height="10.98" bbox="[320.22, 81.624, 535.119, 92.604]" index="14">COMPOSICI&#211;N QU&#205;MICA Y PRINCIPIOS ACTIVOS </LTTextBoxHorizontal></LTTextLineHorizontal>
    <LTTextLineHorizontal y0="63.024" y1="74.004" x0="320.22" x1="541.06" width="220.84" height="10.98" bbox="[320.22, 63.024, 541.06, 74.004]" word_margin="0.1"><LTTextBoxHorizontal y0="63.024" y1="74.004" x0="320.22" x1="541.06" width="220.84" height="10.98" bbox="[320.22, 63.024, 541.06, 74.004]" index="15">Las hojas contienen muc&#237;lago neutro (11%), sales mi- </LTTextBoxHorizontal></LTTextLineHorizontal>
    <LTTextLineHorizontal y0="482.422" y1="493.402" x0="70.921" x1="186.118" width="115.197" height="10.98" bbox="[70.921, 482.422, 186.118, 493.402]" word_margin="0.1"><LTTextBoxHorizontal y0="482.422" y1="493.402" x0="70.921" x1="186.118" width="115.197" height="10.98" bbox="[70.921, 482.422, 186.118, 493.402]" index="16">DESCRIPCI&#211;N BOT&#193;NICA </LTTextBoxHorizontal></LTTextLineHorizontal>
    <LTTextBoxHorizontal y0="388.043" y1="474.741" x0="70.921" x1="294.451" width="223.53" height="86.698" bbox="[70.921, 388.043, 294.451, 474.741]" index="17"><LTTextLineHorizontal y0="463.761" y1="474.741" x0="70.921" x1="294.451" width="223.53" height="10.98" bbox="[70.921, 463.761, 294.451, 474.741]" word_margin="0.1">Planta anual, tallo erecto, 60 cm de alto, cubierto por </LTTextLineHorizontal><LTTextLineHorizontal y0="451.162" y1="462.142" x0="70.921" x1="294.35" width="223.429" height="10.98" bbox="[70.921, 451.162, 294.35, 462.142]" word_margin="0.1">pelitos duros. Hojas alternas, el&#237;pticas, 3-11 cm de </LTTextLineHorizontal><LTTextLineHorizontal y0="438.562" y1="449.542" x0="70.921" x1="294.287" width="223.366" height="10.98" bbox="[70.921, 438.562, 294.287, 449.542]" word_margin="0.1">largo, rugosas, cubiertas de finos pelillos en ambas </LTTextLineHorizontal><LTTextLineHorizontal y0="425.902" y1="436.882" x0="70.921" x1="294.245" width="223.323" height="10.98" bbox="[70.921, 425.902, 294.245, 436.882]" word_margin="0.1">superficies; enteras, s&#233;siles o corto-pecioladas. Flores </LTTextLineHorizontal><LTTextLineHorizontal y0="413.303" y1="424.283" x0="70.921" x1="294.301" width="223.379" height="10.98" bbox="[70.921, 413.303, 294.301, 424.283]" word_margin="0.1">pendulosas, en racimos de pocas flores en el &#225;pice de </LTTextLineHorizontal><LTTextLineHorizontal y0="400.703" y1="411.683" x0="70.921" x1="294.306" width="223.385" height="10.98" bbox="[70.921, 400.703, 294.306, 411.683]" word_margin="0.1">los tallos, 2 cm de di&#225;metro, 5 p&#233;talos, azul brillantes, </LTTextLineHorizontal><LTTextLineHorizontal y0="388.043" y1="399.023" x0="70.921" x1="161.083" width="90.162" height="10.98" bbox="[70.921, 388.043, 161.083, 399.023]" word_margin="0.1">raramente blancas 1,2. </LTTextLineHorizontal></LTTextBoxHorizontal>
    <LTTextLineHorizontal y0="357.443" y1="368.423" x0="70.92" x1="112.997" width="42.077" height="10.98" bbox="[70.92, 357.443, 112.997, 368.423]" word_margin="0.1"><LTTextBoxHorizontal y0="357.443" y1="368.423" x0="70.92" x1="112.997" width="42.077" height="10.98" bbox="[70.92, 357.443, 112.997, 368.423]" index="18">H&#193;BITAT </LTTextBoxHorizontal></LTTextLineHorizontal>
    <LTTextBoxHorizontal y0="288.323" y1="349.823" x0="70.92" x1="294.295" width="223.375" height="61.5" bbox="[70.92, 288.323, 294.295, 349.823]" index="19"><LTTextLineHorizontal y0="338.843" y1="349.823" x0="70.92" x1="291.939" width="221.019" height="10.98" bbox="[70.92, 338.843, 291.939, 349.823]" word_margin="0.1">Planta nativa de Europa y norte de &#193;frica, naturali- </LTTextLineHorizontal><LTTextLineHorizontal y0="326.183" y1="337.163" x0="70.92" x1="291.691" width="220.771" height="10.98" bbox="[70.92, 326.183, 291.691, 337.163]" word_margin="0.1">zada en varias partes del mundo en regiones tem- </LTTextLineHorizontal><LTTextLineHorizontal y0="313.583" y1="324.563" x0="70.92" x1="291.8" width="220.88" height="10.98" bbox="[70.92, 313.583, 291.8, 324.563]" word_margin="0.1">pladas. Se cultiva ocasionalmente en climas tem- </LTTextLineHorizontal><LTTextLineHorizontal y0="300.923" y1="311.904" x0="70.92" x1="294.295" width="223.375" height="10.98" bbox="[70.92, 300.923, 294.295, 311.904]" word_margin="0.1">plados de Mesoam&#233;rica en huertos familiares como </LTTextLineHorizontal><LTTextLineHorizontal y0="288.323" y1="299.304" x0="70.92" x1="201.463" width="130.543" height="10.981" bbox="[70.92, 288.323, 201.463, 299.304]" word_margin="0.1">planta ornamental y medicinal 3. </LTTextLineHorizontal></LTTextBoxHorizontal>
    <LTTextLineHorizontal y0="257.723" y1="268.703" x0="70.92" x1="127.476" width="56.556" height="10.98" bbox="[70.92, 257.723, 127.476, 268.703]" word_margin="0.1"><LTTextBoxHorizontal y0="257.723" y1="268.703" x0="70.92" x1="127.476" width="56.556" height="10.98" bbox="[70.92, 257.723, 127.476, 268.703]" index="20">OBTENCI&#211;N </LTTextBoxHorizontal></LTTextLineHorizontal>
    <LTTextBoxHorizontal y0="112.883" y1="250.043" x0="70.92" x1="294.402" width="223.482" height="137.159" bbox="[70.92, 112.883, 294.402, 250.043]" index="21"><LTTextLineHorizontal y0="239.063" y1="250.043" x0="70.92" x1="294.338" width="223.418" height="10.98" bbox="[70.92, 239.063, 294.338, 250.043]" word_margin="0.1">Cultivada como medicina y alimento en Europa, Norte </LTTextLineHorizontal><LTTextLineHorizontal y0="226.463" y1="237.443" x0="70.92" x1="294.277" width="223.357" height="10.98" bbox="[70.92, 226.463, 294.277, 237.443]" word_margin="0.1">Am&#233;rica y Asia Menor; en suelos livianos, h&#250;medos </LTTextLineHorizontal><LTTextLineHorizontal y0="213.863" y1="224.843" x0="70.92" x1="294.356" width="223.436" height="10.98" bbox="[70.92, 213.863, 294.356, 224.843]" word_margin="0.1">bien drenados. Se siembra directamente a 3-5 cm de </LTTextLineHorizontal><LTTextLineHorizontal y0="201.204" y1="212.184" x0="70.92" x1="294.308" width="223.388" height="10.98" bbox="[70.92, 201.204, 294.308, 212.184]" word_margin="0.1">profundidad y distancia de 25-30 cm entre surcos; es </LTTextLineHorizontal><LTTextLineHorizontal y0="188.604" y1="199.584" x0="70.92" x1="294.233" width="223.313" height="10.98" bbox="[70.92, 188.604, 294.233, 199.584]" word_margin="0.1">de bajo requerimiento nutricional. Un primer corte de </LTTextLineHorizontal><LTTextLineHorizontal y0="176.004" y1="186.984" x0="70.92" x1="291.771" width="220.851" height="10.98" bbox="[70.92, 176.004, 291.771, 186.984]" word_margin="0.1">hojas se hace al iniciar la floraci&#243;n (marzo-septiem- </LTTextLineHorizontal><LTTextLineHorizontal y0="163.344" y1="174.324" x0="70.92" x1="294.307" width="223.387" height="10.98" bbox="[70.92, 163.344, 294.307, 174.324]" word_margin="0.1">bre), se secan a la sombra o por breve exposici&#243;n al </LTTextLineHorizontal><LTTextLineHorizontal y0="150.745" y1="161.725" x0="70.92" x1="294.237" width="223.317" height="10.98" bbox="[70.92, 150.745, 294.237, 161.725]" word_margin="0.1">sol; las semillas se recogen durante todo el a&#241;o, al </LTTextLineHorizontal><LTTextLineHorizontal y0="138.085" y1="149.065" x0="70.92" x1="294.402" width="223.482" height="10.98" bbox="[70.92, 138.085, 294.402, 149.065]" word_margin="0.1">final de la fructificaci&#243;n se obtienen hojas y semillas. </LTTextLineHorizontal><LTTextLineHorizontal y0="125.485" y1="136.465" x0="70.92" x1="294.276" width="223.356" height="10.98" bbox="[70.92, 125.485, 294.276, 136.465]" word_margin="0.1">Pueden sembrarse hasta 36,000 plantas/ha; en el </LTTextLineHorizontal><LTTextLineHorizontal y0="112.883" y1="123.866" x0="70.92" x1="275.743" width="204.823" height="10.982" bbox="[70.92, 112.883, 275.743, 123.866]" word_margin="0.1">caso de semilla puede producir hasta 750 kg/ha 4. </LTTextLineHorizontal></LTTextBoxHorizontal>
    <LTTextLineHorizontal y0="88.223" y1="99.203" x0="70.92" x1="240.26" width="169.339" height="10.98" bbox="[70.92, 88.223, 240.26, 99.203]" word_margin="0.1"><LTTextBoxHorizontal y0="88.223" y1="99.203" x0="70.92" x1="240.26" width="169.339" height="10.98" bbox="[70.92, 88.223, 240.26, 99.203]" index="22">USOS Y PROPIEDADES MEDICINALES </LTTextBoxHorizontal></LTTextLineHorizontal>
    <LTTextLineHorizontal y0="69.623" y1="80.603" x0="70.92" x1="294.278" width="223.357" height="10.98" bbox="[70.92, 69.623, 294.278, 80.603]" word_margin="0.1"><LTTextBoxHorizontal y0="69.623" y1="80.603" x0="70.92" x1="294.278" width="223.357" height="10.98" bbox="[70.92, 69.623, 294.278, 80.603]" index="23">Se usa desde antes de la era cristiana; Plinio y Galeno </LTTextBoxHorizontal></LTTextLineHorizontal>
    <LTTextLineHorizontal y0="31.176" y1="40.221" x0="297.48" x1="316.89" width="19.41" height="9.045" bbox="[297.48, 31.176, 316.89, 40.221]" word_margin="0.1"><LTTextBoxHorizontal y0="31.176" y1="40.221" x0="297.48" x1="316.89" width="19.41" height="9.045" bbox="[297.48, 31.176, 316.89, 40.221]" index="24">- 65 - </LTTextBoxHorizontal></LTTextLineHorizontal>
    <LTRect y0="747.84" y1="748.32" x0="69.42" x1="542.7" width="473.28" height="0.48" bbox="[69.42, 747.84, 542.7, 748.32]" linewidth="0" pts="[[69.42, 747.84], [542.7, 747.84], [542.7, 748.32], [69.42, 748.32]]"/>
    <LTImage y0="500.94" y1="726.84" x0="123.84" x1="238.92" width="115.08" height="225.9" bbox="[123.84, 500.94, 238.92, 726.84]" name="Im0" colorspace="[&quot;&lt;PDFObjRef:725&gt;&quot;]" bits="8" imagemask="null" srcsize="[294, 600]" stream="&lt;PDFStream(171): raw=23184, {'Length': 23184, 'Filter': /'DCTDecode', 'Width': 294, 'Height': 600, 'BitsPerComponent': 8, 'ColorSpace': &lt;PDFObjRef:725&gt;, 'Type': /'XObject', 'Subtype': /'Image'}&gt;">
      <LTFigure y0="500.94" y1="726.84" x0="123.84" x1="238.92" width="115.08" height="225.9" bbox="[123.84, 500.94, 238.92, 726.84]" name="Im0" matrix="[115.08, 0.0, 0.0, 225.9, 123.84, 500.94]"/>
    </LTImage>
    <LTRect y0="688.08" y1="716.64" x0="328.68" x1="546.66" width="217.98" height="28.56" bbox="[328.68, 688.08, 546.66, 716.64]" linewidth="0" pts="[[328.68, 688.08], [546.66, 688.08], [546.66, 716.64], [328.68, 716.64]]"/>
    <LTRect y0="716.64" y1="717.12" x0="328.2" x1="547.14" width="218.94" height="0.48" bbox="[328.2, 716.64, 547.14, 717.12]" linewidth="0" pts="[[328.2, 716.64], [547.14, 716.64], [547.14, 717.12], [328.2, 717.12]]">
      <LTRect y0="716.64" y1="717.12" x0="328.2" x1="328.68" width="0.48" height="0.48" bbox="[328.2, 716.64, 328.68, 717.12]" linewidth="0" pts="[[328.2, 716.64], [328.68, 716.64], [328.68, 717.12], [328.2, 717.12]]"/>
      <LTRect y0="716.64" y1="717.12" x0="546.66" x1="547.14" width="0.48" height="0.48" bbox="[546.66, 716.64, 547.14, 717.12]" linewidth="0" pts="[[546.66, 716.64], [547.14, 716.64], [547.14, 717.12], [546.66, 717.12]]"/>
    </LTRect>
    <LTRect y0="688.08" y1="716.64" x0="328.2" x1="328.68" width="0.48" height="28.56" bbox="[328.2, 688.08, 328.68, 716.64]" linewidth="0" pts="[[328.2, 688.08], [328.68, 688.08], [328.68, 716.64], [328.2, 716.64]]"/>
    <LTRect y0="688.08" y1="716.64" x0="546.66" x1="547.62" width="0.96" height="28.56" bbox="[546.66, 688.08, 547.62, 716.64]" linewidth="0" pts="[[546.66, 688.08], [547.62, 688.08], [547.62, 716.64], [546.66, 716.64]]"/>
    <LTRect y0="675.42" y1="688.08" x0="328.2" x1="328.68" width="0.48" height="12.66" bbox="[328.2, 675.42, 328.68, 688.08]" linewidth="0" pts="[[328.2, 675.42], [328.68, 675.42], [328.68, 688.08], [328.2, 688.08]]"/>
    <LTRect y0="675.42" y1="688.08" x0="546.66" x1="547.62" width="0.96" height="12.66" bbox="[546.66, 675.42, 547.62, 688.08]" linewidth="0" pts="[[546.66, 675.42], [547.62, 675.42], [547.62, 688.08], [546.66, 688.08]]"/>
    <LTRect y0="662.46" y1="662.94" x0="328.2" x1="328.68" width="0.48" height="0.48" bbox="[328.2, 662.46, 328.68, 662.94]" linewidth="0" pts="[[328.2, 662.46], [328.68, 662.46], [328.68, 662.94], [328.2, 662.94]]">
      <LTRect y0="662.46" y1="662.94" x0="328.2" x1="328.68" width="0.48" height="0.48" bbox="[328.2, 662.46, 328.68, 662.94]" linewidth="0" pts="[[328.2, 662.46], [328.68, 662.46], [328.68, 662.94], [328.2, 662.94]]"/>
    </LTRect>
    <LTRect y0="661.98" y1="662.94" x0="328.68" x1="546.66" width="217.98" height="0.96" bbox="[328.68, 661.98, 546.66, 662.94]" linewidth="0" pts="[[328.68, 661.98], [546.66, 661.98], [546.66, 662.94], [328.68, 662.94]]"/>
    <LTRect y0="661.98" y1="662.94" x0="547.14" x1="547.62" width="0.48" height="0.96" bbox="[547.14, 661.98, 547.62, 662.94]" linewidth="0" pts="[[547.14, 661.98], [547.62, 661.98], [547.62, 662.94], [547.14, 662.94]]"/>
    <LTRect y0="661.98" y1="662.46" x0="546.66" x1="547.62" width="0.96" height="0.48" bbox="[546.66, 661.98, 547.62, 662.46]" linewidth="0" pts="[[546.66, 661.98], [547.62, 661.98], [547.62, 662.46], [546.66, 662.46]]"/>
    <LTRect y0="662.46" y1="662.94" x0="546.66" x1="547.14" width="0.48" height="0.48" bbox="[546.66, 662.46, 547.14, 662.94]" linewidth="0" pts="[[546.66, 662.46], [547.14, 662.46], [547.14, 662.94], [546.66, 662.94]]">
      <LTRect y0="662.46" y1="662.94" x0="546.66" x1="547.14" width="0.48" height="0.48" bbox="[546.66, 662.46, 547.14, 662.94]" linewidth="0" pts="[[546.66, 662.46], [547.14, 662.46], [547.14, 662.94], [546.66, 662.94]]"/>
    </LTRect>
    <LTRect y0="662.94" y1="675.42" x0="328.2" x1="328.68" width="0.48" height="12.48" bbox="[328.2, 662.94, 328.68, 675.42]" linewidth="0" pts="[[328.2, 662.94], [328.68, 662.94], [328.68, 675.42], [328.2, 675.42]]"/>
    <LTRect y0="662.94" y1="675.42" x0="546.66" x1="547.62" width="0.96" height="12.48" bbox="[546.66, 662.94, 547.62, 675.42]" linewidth="0" pts="[[546.66, 662.94], [547.62, 662.94], [547.62, 675.42], [546.66, 675.42]]"/>
    <LTRect y0="42.42" y1="42.9" x0="69.42" x1="542.7" width="473.28" height="0.48" bbox="[69.42, 42.42, 542.7, 42.9]" linewidth="0" pts="[[69.42, 42.42], [542.7, 42.42], [542.7, 42.9], [69.42, 42.9]]"/>
    <LTTextLineHorizontal y0="717.776" y1="725.756" x0="430.68" x1="432.499" width="1.819" height="7.98" bbox="[430.68, 717.776, 432.499, 725.756]" word_margin="0.1"> </LTTextLineHorizontal>
    <LTTextLineHorizontal y0="649.403" y1="660.383" x0="320.22" x1="322.723" width="2.503" height="10.98" bbox="[320.22, 649.403, 322.723, 660.383]" word_margin="0.1"> </LTTextLineHorizontal>
    <LTTextLineHorizontal y0="612.143" y1="623.123" x0="320.22" x1="322.723" width="2.503" height="10.98" bbox="[320.22, 612.143, 322.723, 623.123]" word_margin="0.1"> </LTTextLineHorizontal>
    <LTTextLineHorizontal y0="562.882" y1="573.862" x0="541.14" x1="543.643" width="2.503" height="10.98" bbox="[541.14, 562.882, 543.643, 573.862]" word_margin="0.1"> </LTTextLineHorizontal>
    <LTTextLineHorizontal y0="495.021" y1="506.001" x0="541.141" x1="543.644" width="2.503" height="10.98" bbox="[541.141, 495.021, 543.644, 506.001]" word_margin="0.1"> </LTTextLineHorizontal>
  </LTPage>
  <LTPage y0="0" y1="792" x0="0" x1="612" width="612" height="792" bbox="[0, 0, 612, 792]" pageid="2" rotate="0" page_index="65" page_label="">
    <LTTextLineHorizontal y0="749.266" y1="759.286" x0="222.66" x1="391.745" width="169.085" height="10.02" bbox="[222.66, 749.266, 391.745, 759.286]" word_margin="0.1"><LTTextBoxHorizontal y0="749.266" y1="759.286" x0="222.66" x1="391.745" width="169.085" height="10.02" bbox="[222.66, 749.266, 391.745, 759.286]" index="0">Vadem&#233;cum Nacional de Plantas Medicinales </LTTextBoxHorizontal></LTTextLineHorizontal>
    <LTTextBoxHorizontal y0="663.743" y1="725.183" x0="70.92" x1="296.863" width="225.943" height="61.44" bbox="[70.92, 663.743, 296.863, 725.183]" index="1"><LTTextLineHorizontal y0="714.203" y1="725.183" x0="70.92" x1="294.292" width="223.372" height="10.98" bbox="[70.92, 714.203, 294.292, 725.183]" word_margin="0.1">nerales (s&#237;lice, calcio, potasio), resinas, antocianinas, </LTTextLineHorizontal><LTTextLineHorizontal y0="701.604" y1="712.584" x0="70.92" x1="291.822" width="220.902" height="10.98" bbox="[70.92, 701.604, 291.822, 712.584]" word_margin="0.1">alcaloides pirrolizid&#237;nicos (amabilina, licopsamina, tsi- </LTTextLineHorizontal><LTTextLineHorizontal y0="689.003" y1="699.984" x0="70.92" x1="296.863" width="225.943" height="10.981" bbox="[70.92, 689.003, 296.863, 699.984]" word_margin="0.1">nina, viridiflorato de supinidina) y prostaglandinas 12,13. </LTTextLineHorizontal><LTTextLineHorizontal y0="676.343" y1="687.323" x0="70.92" x1="294.37" width="223.45" height="10.98" bbox="[70.92, 676.343, 294.37, 687.323]" word_margin="0.1">Las semillas contienen alanto&#237;na y un aceite fijo rico en </LTTextLineHorizontal><LTTextLineHorizontal y0="663.743" y1="674.724" x0="70.92" x1="289.483" width="218.563" height="10.98" bbox="[70.92, 663.743, 289.483, 674.724]" word_margin="0.1">&#225;cido oleico, linoleico, palm&#237;tico y &#947;-linoleico (GLA) 14. </LTTextLineHorizontal></LTTextBoxHorizontal>
    <LTTextBoxHorizontal y0="582.024" y1="656.063" x0="70.92" x1="294.309" width="223.389" height="74.038" bbox="[70.92, 582.024, 294.309, 656.063]" index="2"><LTTextLineHorizontal y0="645.083" y1="656.063" x0="70.92" x1="294.302" width="223.382" height="10.98" bbox="[70.92, 645.083, 294.302, 656.063]" word_margin="0.1">La materia m&#233;dica son las hojas y semillas secas que </LTTextLineHorizontal><LTTextLineHorizontal y0="632.483" y1="643.463" x0="70.92" x1="291.739" width="220.819" height="10.98" bbox="[70.92, 632.483, 291.739, 643.463]" word_margin="0.1">deben reunir las mismas caracter&#237;sticas fisicoqu&#237;mi- </LTTextLineHorizontal><LTTextLineHorizontal y0="619.884" y1="630.864" x0="70.92" x1="291.692" width="220.772" height="10.98" bbox="[70.92, 619.884, 291.692, 630.864]" word_margin="0.1">cas y sanitarias de la materia prima usada para ela- </LTTextLineHorizontal><LTTextLineHorizontal y0="607.224" y1="618.204" x0="70.92" x1="294.309" width="223.389" height="10.98" bbox="[70.92, 607.224, 294.309, 618.204]" word_margin="0.1">borar productos fitofarmac&#233;uticos. En la revisi&#243;n </LTTextLineHorizontal><LTTextLineHorizontal y0="594.624" y1="605.604" x0="70.92" x1="294.295" width="223.375" height="10.98" bbox="[70.92, 594.624, 294.295, 605.604]" word_margin="0.1">realizada no se encontraron estudios tendientes a la </LTTextLineHorizontal><LTTextLineHorizontal y0="582.024" y1="593.004" x0="70.92" x1="250.423" width="179.503" height="10.98" bbox="[70.92, 582.024, 250.423, 593.004]" word_margin="0.1">formulaci&#243;n de productos fitofarmac&#233;uticos. </LTTextLineHorizontal></LTTextBoxHorizontal>
    <LTTextBoxHorizontal y0="487.643" y1="574.344" x0="70.92" x1="294.328" width="223.409" height="86.701" bbox="[70.92, 487.643, 294.328, 574.344]" index="3"><LTTextLineHorizontal y0="563.364" y1="574.344" x0="70.92" x1="136.92" width="66.001" height="10.98" bbox="[70.92, 563.364, 136.92, 574.344]" word_margin="0.1">Los muc&#237;lagos </LTTextLineHorizontal><LTTextLineHorizontal y0="563.364" y1="574.344" x0="142.277" x1="294.288" width="152.012" height="10.98" bbox="[142.277, 563.364, 294.288, 574.344]" word_margin="0.1">le confieren propiedad emoliente, </LTTextLineHorizontal><LTTextLineHorizontal y0="550.764" y1="561.744" x0="70.92" x1="294.328" width="223.409" height="10.98" bbox="[70.92, 550.764, 294.328, 561.744]" word_margin="0.1">antiinflamatoria y bals&#225;mica; las sales de potasio y los </LTTextLineHorizontal><LTTextLineHorizontal y0="538.165" y1="549.145" x0="70.92" x1="294.237" width="223.318" height="10.98" bbox="[70.92, 538.165, 294.237, 549.145]" word_margin="0.1">flavonoides, una actividad diur&#233;tica y sudor&#237;fica por </LTTextLineHorizontal><LTTextLineHorizontal y0="525.505" y1="536.485" x0="70.92" x1="291.726" width="220.806" height="10.98" bbox="[70.92, 525.505, 291.726, 536.485]" word_margin="0.1">acci&#243;n directa sobre el epitelio renal. El efecto expec- </LTTextLineHorizontal><LTTextLineHorizontal y0="512.905" y1="523.885" x0="70.92" x1="294.236" width="223.316" height="10.98" bbox="[70.92, 512.905, 294.236, 523.885]" word_margin="0.1">torante est&#225; dado por la acci&#243;n antiinflamatoria sobre </LTTextLineHorizontal><LTTextLineHorizontal y0="500.245" y1="511.225" x0="70.92" x1="294.303" width="223.383" height="10.98" bbox="[70.92, 500.245, 294.303, 511.225]" word_margin="0.1">la mucosa bronquial y la fluidificaci&#243;n secundaria, lo </LTTextLineHorizontal><LTTextLineHorizontal y0="487.643" y1="498.626" x0="70.92" x1="236.263" width="165.343" height="10.982" bbox="[70.92, 487.643, 236.263, 498.626]" word_margin="0.1">que contribuye a la sedaci&#243;n de la tos 15. </LTTextLineHorizontal></LTTextBoxHorizontal>
    <LTTextBoxHorizontal y0="342.803" y1="480.023" x0="70.92" x1="294.366" width="223.446" height="137.22" bbox="[70.92, 342.803, 294.366, 480.023]" index="4"><LTTextLineHorizontal y0="469.043" y1="480.023" x0="70.92" x1="294.298" width="223.378" height="10.98" bbox="[70.92, 469.043, 294.298, 480.023]" word_margin="0.1">El GLA presente en las semillas es un &#225;cido graso </LTTextLineHorizontal><LTTextLineHorizontal y0="456.383" y1="467.363" x0="70.92" x1="294.342" width="223.422" height="10.98" bbox="[70.92, 456.383, 294.342, 467.363]" word_margin="0.1">esencial soluble en disolventes org&#225;nicos. Es un </LTTextLineHorizontal><LTTextLineHorizontal y0="443.784" y1="454.764" x0="70.92" x1="291.807" width="220.887" height="10.98" bbox="[70.92, 443.784, 291.807, 454.764]" word_margin="0.1">metabolito poco com&#250;n pero importante como inter- </LTTextLineHorizontal><LTTextLineHorizontal y0="431.184" y1="442.164" x0="70.92" x1="294.355" width="223.435" height="10.98" bbox="[70.92, 431.184, 294.355, 442.164]" word_margin="0.1">mediario en la bios&#237;ntesis de prostaglandinas; como </LTTextLineHorizontal><LTTextLineHorizontal y0="418.524" y1="429.504" x0="70.92" x1="294.366" width="223.446" height="10.98" bbox="[70.92, 418.524, 294.366, 429.504]" word_margin="0.1">suplemento alimenticio ayuda en enfermedades por </LTTextLineHorizontal><LTTextLineHorizontal y0="405.924" y1="416.904" x0="70.92" x1="291.759" width="220.839" height="10.98" bbox="[70.92, 405.924, 291.759, 416.904]" word_margin="0.1">deficiencia de &#225;cidos grasos esenciales; ha demos- </LTTextLineHorizontal><LTTextLineHorizontal y0="393.325" y1="404.305" x0="70.92" x1="291.737" width="220.817" height="10.98" bbox="[70.92, 393.325, 291.737, 404.305]" word_margin="0.1">trado importante efecto terap&#233;utico en el eczema at&#243;- </LTTextLineHorizontal><LTTextLineHorizontal y0="380.665" y1="391.645" x0="70.92" x1="294.3" width="223.38" height="10.98" bbox="[70.92, 380.665, 294.3, 391.645]" word_margin="0.1">pico, s&#237;ndrome premestrual, diabetes, alcoholismo e </LTTextLineHorizontal><LTTextLineHorizontal y0="368.065" y1="379.045" x0="70.92" x1="121.463" width="50.543" height="10.98" bbox="[70.92, 368.065, 121.463, 379.045]" word_margin="0.1">inflamaci&#243;n; </LTTextLineHorizontal><LTTextLineHorizontal y0="368.065" y1="379.045" x0="126.579" x1="294.306" width="167.727" height="10.98" bbox="[126.579, 368.065, 294.306, 379.045]" word_margin="0.1">tiene propiedad hipocolesterolemiante, </LTTextLineHorizontal><LTTextLineHorizontal y0="355.405" y1="366.385" x0="70.92" x1="291.811" width="220.891" height="10.98" bbox="[70.92, 355.405, 291.811, 366.385]" word_margin="0.1">antidisminorr&#233;ica y reguladora hormonal y del meta- </LTTextLineHorizontal><LTTextLineHorizontal y0="342.803" y1="353.786" x0="70.92" x1="148.483" width="77.563" height="10.982" bbox="[70.92, 342.803, 148.483, 353.786]" word_margin="0.1">bolismo general 16. </LTTextLineHorizontal></LTTextBoxHorizontal>
    <LTTextLineHorizontal y0="312.203" y1="323.183" x0="70.92" x1="136.52" width="65.6" height="10.98" bbox="[70.92, 312.203, 136.52, 323.183]" word_margin="0.1"><LTTextBoxHorizontal y0="312.203" y1="323.183" x0="70.92" x1="136.52" width="65.6" height="10.98" bbox="[70.92, 312.203, 136.52, 323.183]" index="5">TOXICOLOG&#205;A </LTTextBoxHorizontal></LTTextLineHorizontal>
    <LTTextBoxHorizontal y0="230.423" y1="304.523" x0="70.92" x1="294.383" width="223.464" height="74.099" bbox="[70.92, 230.423, 294.383, 304.523]" index="6"><LTTextLineHorizontal y0="293.543" y1="304.523" x0="70.92" x1="294.383" width="223.464" height="10.98" bbox="[70.92, 293.543, 294.383, 304.523]" word_margin="0.1">Los pelitos de las hojas y tallo pueden ser irritantes. </LTTextLineHorizontal><LTTextLineHorizontal y0="280.943" y1="291.923" x0="70.92" x1="294.307" width="223.387" height="10.98" bbox="[70.92, 280.943, 294.307, 291.923]" word_margin="0.1">Los alcaloides pirrolizid&#237;nicos insaturados (amabilina, </LTTextLineHorizontal><LTTextLineHorizontal y0="268.343" y1="279.323" x0="70.92" x1="291.675" width="220.755" height="10.98" bbox="[70.92, 268.343, 291.675, 279.323]" word_margin="0.1">licopsamina) pueden ser hepatot&#243;xicos y potencial- </LTTextLineHorizontal><LTTextLineHorizontal y0="255.684" y1="266.664" x0="70.92" x1="294.271" width="223.351" height="10.98" bbox="[70.92, 255.684, 294.271, 266.664]" word_margin="0.1">mente carcinog&#233;nicos, pero la baja concentraci&#243;n de </LTTextLineHorizontal><LTTextLineHorizontal y0="243.084" y1="254.064" x0="70.92" x1="294.323" width="223.403" height="10.98" bbox="[70.92, 243.084, 294.323, 254.064]" word_margin="0.1">sus alcaloides le dan cierto margen de seguridad, no </LTTextLineHorizontal><LTTextLineHorizontal y0="230.423" y1="241.404" x0="70.92" x1="285.883" width="214.964" height="10.981" bbox="[70.92, 230.423, 285.883, 241.404]" word_margin="0.1">se recomienda usar la hoja por tiempo prolongado 17. </LTTextLineHorizontal></LTTextBoxHorizontal>
    <LTTextLineHorizontal y0="199.823" y1="210.803" x0="70.92" x1="177.564" width="106.644" height="10.98" bbox="[70.92, 199.823, 177.564, 210.803]" word_margin="0.1"><LTTextBoxHorizontal y0="199.823" y1="210.803" x0="70.92" x1="177.564" width="106.644" height="10.98" bbox="[70.92, 199.823, 177.564, 210.803]" index="7">CONTRAINDICACIONES </LTTextBoxHorizontal></LTTextLineHorizontal>
    <LTTextBoxHorizontal y0="155.963" y1="192.203" x0="70.92" x1="294.366" width="223.446" height="36.24" bbox="[70.92, 155.963, 294.366, 192.203]" index="8"><LTTextLineHorizontal y0="181.223" y1="192.203" x0="70.92" x1="294.366" width="223.446" height="10.98" bbox="[70.92, 181.223, 294.366, 192.203]" word_margin="0.1">Por su contenido de alcaloides pirrolizid&#237;nicos, las </LTTextLineHorizontal><LTTextLineHorizontal y0="168.563" y1="179.543" x0="70.92" x1="291.799" width="220.878" height="10.98" bbox="[70.92, 168.563, 291.799, 179.543]" word_margin="0.1">hojas estan contraindicadas en pacientes con hepato- </LTTextLineHorizontal><LTTextLineHorizontal y0="155.963" y1="166.944" x0="70.92" x1="243.283" width="172.363" height="10.98" bbox="[70.92, 155.963, 243.283, 166.944]" word_margin="0.1">pat&#237;as, neoplasia, embarazo y lactancia 18. </LTTextLineHorizontal></LTTextBoxHorizontal>
    <LTTextLineHorizontal y0="125.363" y1="136.343" x0="70.92" x1="269.749" width="198.828" height="10.98" bbox="[70.92, 125.363, 269.749, 136.343]" word_margin="0.1"><LTTextBoxHorizontal y0="125.363" y1="136.343" x0="70.92" x1="269.749" width="198.828" height="10.98" bbox="[70.92, 125.363, 269.749, 136.343]" index="9">PRECAUCIONES Y REACCIONES ADVERSAS </LTTextBoxHorizontal></LTTextLineHorizontal>
    <LTTextBoxHorizontal y0="81.503" y1="117.683" x0="70.92" x1="294.297" width="223.377" height="36.179" bbox="[70.92, 81.503, 294.297, 117.683]" index="10"><LTTextLineHorizontal y0="106.703" y1="117.683" x0="70.92" x1="294.287" width="223.367" height="10.98" bbox="[70.92, 106.703, 294.287, 117.683]" word_margin="0.1">El alcaloide senecionina puede producir enfermedad </LTTextLineHorizontal><LTTextLineHorizontal y0="94.103" y1="105.083" x0="70.92" x1="291.753" width="220.833" height="10.98" bbox="[70.92, 94.103, 291.753, 105.083]" word_margin="0.1">venoclusiva hep&#225;tica. El aceite puede producir algu- </LTTextLineHorizontal><LTTextLineHorizontal y0="81.503" y1="92.483" x0="70.92" x1="294.297" width="223.377" height="10.98" bbox="[70.92, 81.503, 294.297, 92.483]" word_margin="0.1">nos casos de metahemoglobinemia y trastornos del </LTTextLineHorizontal></LTTextBoxHorizontal>
    <LTTextLineHorizontal y0="714.204" y1="725.184" x0="320.22" x1="435.005" width="114.785" height="10.98" bbox="[320.22, 714.204, 435.005, 725.184]" word_margin="0.1"><LTTextBoxHorizontal y0="714.204" y1="725.184" x0="320.22" x1="435.005" width="114.785" height="10.98" bbox="[320.22, 714.204, 435.005, 725.184]" index="11">medio uterino en pediatr&#237;a. </LTTextBoxHorizontal></LTTextLineHorizontal>
    <LTTextLineHorizontal y0="683.604" y1="694.584" x0="320.22" x1="461.028" width="140.808" height="10.98" bbox="[320.22, 683.604, 461.028, 694.584]" word_margin="0.1"><LTTextBoxHorizontal y0="683.604" y1="694.584" x0="320.22" x1="461.028" width="140.808" height="10.98" bbox="[320.22, 683.604, 461.028, 694.584]" index="12">INDICACIONES TERAP&#201;UTICAS </LTTextBoxHorizontal></LTTextLineHorizontal>
    <LTTextBoxHorizontal y0="614.483" y1="675.984" x0="320.22" x1="546.221" width="226.001" height="61.5" bbox="[320.22, 614.483, 546.221, 675.984]" index="13"><LTTextLineHorizontal y0="665.004" y1="675.984" x0="320.22" x1="543.579" width="223.359" height="10.98" bbox="[320.22, 665.004, 543.579, 675.984]" word_margin="0.1">Las hojas son de amplio uso popular, aunque no son </LTTextLineHorizontal><LTTextLineHorizontal y0="652.344" y1="663.324" x0="320.22" x1="543.575" width="223.355" height="10.98" bbox="[320.22, 652.344, 543.575, 663.324]" word_margin="0.1">oficinales en la mayor&#237;a de pa&#237;ses. El aceite es </LTTextLineHorizontal><LTTextLineHorizontal y0="639.744" y1="650.724" x0="320.22" x1="546.221" width="226.001" height="10.98" bbox="[320.22, 639.744, 546.221, 650.724]" word_margin="0.1">aceptado como suplemento alimentario por el FDA. </LTTextLineHorizontal><LTTextLineHorizontal y0="627.084" y1="638.064" x0="320.22" x1="543.639" width="223.419" height="10.98" bbox="[320.22, 627.084, 543.639, 638.064]" word_margin="0.1">Existen en el mercado preparaciones gal&#233;nicas como </LTTextLineHorizontal><LTTextLineHorizontal y0="614.483" y1="625.464" x0="320.22" x1="497.563" width="177.343" height="10.981" bbox="[320.22, 614.483, 497.563, 625.464]" word_margin="0.1">extractos, tinturas y c&#225;psulas de aceite 19,20. </LTTextLineHorizontal></LTTextBoxHorizontal>
    <LTTextBoxHorizontal y0="558.024" y1="606.863" x0="320.22" x1="543.573" width="223.354" height="48.839" bbox="[320.22, 558.024, 543.573, 606.863]" index="14"><LTTextLineHorizontal y0="595.883" y1="606.863" x0="320.22" x1="541.09" width="220.87" height="10.98" bbox="[320.22, 595.883, 541.09, 606.863]" word_margin="0.1">Por v&#237;a oral, las hojas est&#225;n indicadas en el tratamien- </LTTextLineHorizontal><LTTextLineHorizontal y0="583.223" y1="594.203" x0="320.22" x1="543.531" width="223.311" height="10.98" bbox="[320.22, 583.223, 543.531, 594.203]" word_margin="0.1">to de afecciones respiratorias (resfriados, bronquitis, </LTTextLineHorizontal><LTTextLineHorizontal y0="570.624" y1="581.604" x0="320.22" x1="543.573" width="223.354" height="10.98" bbox="[320.22, 570.624, 543.573, 581.604]" word_margin="0.1">faringitis), situaciones que requieren aumento de la </LTTextLineHorizontal><LTTextLineHorizontal y0="558.024" y1="569.004" x0="320.22" x1="461.062" width="140.842" height="10.98" bbox="[320.22, 558.024, 461.062, 569.004]" word_margin="0.1">diuresis y s&#237;ndrome premenstrual. </LTTextLineHorizontal></LTTextBoxHorizontal>
    <LTTextBoxHorizontal y0="514.164" y1="550.343" x0="320.22" x1="541.049" width="220.829" height="36.179" bbox="[320.22, 514.164, 541.049, 550.343]" index="15"><LTTextLineHorizontal y0="539.363" y1="550.343" x0="320.22" x1="541.049" width="220.829" height="10.98" bbox="[320.22, 539.363, 541.049, 550.343]" word_margin="0.1">El aceite de las semillas esta indicado en la hiperco- </LTTextLineHorizontal><LTTextLineHorizontal y0="526.764" y1="537.744" x0="320.22" x1="541.042" width="220.823" height="10.98" bbox="[320.22, 526.764, 541.042, 537.744]" word_margin="0.1">lesterolemia, prevenci&#243;n de la ateroesclerosis, s&#237;ndro- </LTTextLineHorizontal><LTTextLineHorizontal y0="514.164" y1="525.144" x0="320.22" x1="498.17" width="177.95" height="10.98" bbox="[320.22, 514.164, 498.17, 525.144]" word_margin="0.1">me premenstrual y trastornos del climaterio. </LTTextLineHorizontal></LTTextBoxHorizontal>
    <LTTextBoxHorizontal y0="482.904" y1="506.484" x0="320.22" x1="543.598" width="223.378" height="23.58" bbox="[320.22, 482.904, 543.598, 506.484]" index="16"><LTTextLineHorizontal y0="495.504" y1="506.484" x0="320.22" x1="543.598" width="223.378" height="10.98" bbox="[320.22, 495.504, 543.598, 506.484]" word_margin="0.1">T&#243;picamente se preparan cataplasmas de hojas por su </LTTextLineHorizontal><LTTextLineHorizontal y0="482.904" y1="493.884" x0="320.22" x1="463.618" width="143.398" height="10.98" bbox="[320.22, 482.904, 463.618, 493.884]" word_margin="0.1">acci&#243;n antiinflamatoria y emoliente. </LTTextLineHorizontal></LTTextBoxHorizontal>
    <LTTextLineHorizontal y0="452.244" y1="463.224" x0="320.22" x1="474.53" width="154.31" height="10.98" bbox="[320.22, 452.244, 474.53, 463.224]" word_margin="0.1"><LTTextBoxHorizontal y0="452.244" y1="463.224" x0="320.22" x1="474.53" width="154.31" height="10.98" bbox="[320.22, 452.244, 474.53, 463.224]" index="17">FORMAS GAL&#201;NICAS/POSOLOG&#205;A </LTTextBoxHorizontal></LTTextLineHorizontal>
    <LTTextBoxHorizontal y0="421.044" y1="444.624" x0="320.22" x1="543.642" width="223.422" height="23.58" bbox="[320.22, 421.044, 543.642, 444.624]" index="18"><LTTextLineHorizontal y0="433.644" y1="444.624" x0="320.22" x1="543.642" width="223.422" height="10.98" bbox="[320.22, 433.644, 543.642, 444.624]" word_margin="0.1">Administrar 2-3 veces/d&#237;a despu&#233;s de las comidas </LTTextLineHorizontal><LTTextLineHorizontal y0="421.044" y1="432.024" x0="320.22" x1="459.097" width="138.877" height="10.98" bbox="[320.22, 421.044, 459.097, 432.024]" word_margin="0.1">durante 2-3 semanas en dosis de: </LTTextLineHorizontal></LTTextBoxHorizontal>
    <LTTextBoxHorizontal y0="361.496" y1="412.644" x0="320.216" x1="519.728" width="199.512" height="51.148" bbox="[320.216, 361.496, 519.728, 412.644]" index="19"><LTTextLineHorizontal y0="401.576" y1="412.644" x0="320.22" x1="519.728" width="199.508" height="11.068" bbox="[320.22, 401.576, 519.728, 412.644]" word_margin="0.1">&#8226; 3-5 g/taza de la infusi&#243;n, beber 2-3 veces/d&#237;a. </LTTextLineHorizontal><LTTextLineHorizontal y0="388.196" y1="399.264" x0="320.219" x1="510.623" width="190.404" height="11.068" bbox="[320.219, 388.196, 510.623, 399.264]" word_margin="0.1">&#8226; 3-5 ml/d&#237;a de la tintura 1:8 en alcohol 40%. </LTTextLineHorizontal><LTTextLineHorizontal y0="374.876" y1="385.944" x0="320.217" x1="452.931" width="132.713" height="11.068" bbox="[320.217, 374.876, 452.931, 385.944]" word_margin="0.1">&#8226; 1-4 ml/d&#237;a del extracto flu&#237;do </LTTextLineHorizontal><LTTextLineHorizontal y0="361.496" y1="372.564" x0="320.216" x1="471.465" width="151.248" height="11.068" bbox="[320.216, 361.496, 471.465, 372.564]" word_margin="0.1">&#8226; 1-3 c&#225;psulas de 75 mg del aceite. </LTTextLineHorizontal></LTTextBoxHorizontal>
    <LTTextLineHorizontal y0="330.925" y1="341.905" x0="320.215" x1="384.874" width="64.659" height="10.98" bbox="[320.215, 330.925, 384.874, 341.905]" word_margin="0.1"><LTTextBoxHorizontal y0="330.925" y1="341.905" x0="320.215" x1="384.874" width="64.659" height="10.98" bbox="[320.215, 330.925, 384.874, 341.905]" index="20">REFERENCIAS </LTTextBoxHorizontal></LTTextLineHorizontal>
    <LTTextBoxHorizontal y0="89.036" y1="314.814" x0="320.22" x1="537.603" width="217.383" height="225.778" bbox="[320.22, 89.036, 537.603, 314.814]" index="21"><LTTextLineHorizontal y0="305.661" y1="314.814" x0="320.22" x1="506.045" width="185.825" height="9.153" bbox="[320.22, 305.661, 506.045, 314.814]" word_margin="0.1">1 V ol&#225;k J, Stodola J (1984) Plantes M&#233;dicinales, p. 95. </LTTextLineHorizontal><LTTextLineHorizontal y0="294.321" y1="303.474" x0="320.22" x1="462.135" width="141.915" height="9.153" bbox="[320.22, 294.321, 462.135, 303.474]" word_margin="0.1">2 Fl&#252;ck H (1988) Medicinal Plants, p. 120. </LTTextLineHorizontal><LTTextLineHorizontal y0="282.981" y1="292.134" x0="320.22" x1="437.948" width="117.728" height="9.153" bbox="[320.22, 282.981, 437.948, 292.134]" word_margin="0.1">3 Williams LO (1981) Ceiba 24:56. </LTTextLineHorizontal><LTTextLineHorizontal y0="271.701" y1="280.854" x0="320.22" x1="496.988" width="176.768" height="9.153" bbox="[320.22, 271.701, 496.988, 280.854]" word_margin="0.1">4 C&#225;ceres A (1996) Plantas de Uso Medicinal, p. 99. </LTTextLineHorizontal><LTTextLineHorizontal y0="260.361" y1="269.514" x0="320.22" x1="489.244" width="169.024" height="9.153" bbox="[320.22, 260.361, 489.244, 269.514]" word_margin="0.1">5 Font Quer P (1976) Plantas Medicinales, p. 550. </LTTextLineHorizontal><LTTextLineHorizontal y0="249.021" y1="258.174" x0="320.22" x1="533.112" width="212.892" height="9.153" bbox="[320.22, 249.021, 533.112, 258.174]" word_margin="0.1">6 Kowalchik C, Hylton WH (1987) Encyclopedia of Herbs, p. 52. </LTTextLineHorizontal><LTTextLineHorizontal y0="237.681" y1="246.834" x0="320.22" x1="504.009" width="183.789" height="9.153" bbox="[320.22, 237.681, 504.009, 246.834]" word_margin="0.1">7 Duke JA (1985) Handbook of Medicinal Herbs, p. 81. </LTTextLineHorizontal><LTTextLineHorizontal y0="226.401" y1="235.554" x0="320.22" x1="499.513" width="179.293" height="9.153" bbox="[320.22, 226.401, 499.513, 235.554]" word_margin="0.1">8 C&#225;ceres A et al. (1991) J. Ethnopharmacol. 31:193. </LTTextLineHorizontal><LTTextLineHorizontal y0="215.061" y1="224.214" x0="320.22" x1="499.513" width="179.293" height="9.153" bbox="[320.22, 215.061, 499.513, 224.214]" word_margin="0.1">9 C&#225;ceres A et al. (1987) J. Ethnopharmacol. 19:233. </LTTextLineHorizontal><LTTextLineHorizontal y0="202.496" y1="212.516" x0="320.22" x1="509.385" width="189.165" height="10.02" bbox="[320.22, 202.496, 509.385, 212.516]" word_margin="0.1">10 Wettasinghe M, Shahidi F (1999) Food Chem. 67:399. </LTTextLineHorizontal><LTTextLineHorizontal y0="191.241" y1="200.394" x0="320.22" x1="492.491" width="172.271" height="9.153" bbox="[320.22, 191.241, 492.491, 200.394]" word_margin="0.1">11 Pi&#241;eros J et al. (1988) Extractos Naturales, p. 17. </LTTextLineHorizontal><LTTextLineHorizontal y0="179.901" y1="189.054" x0="320.22" x1="503.175" width="182.955" height="9.153" bbox="[320.22, 179.901, 503.175, 189.054]" word_margin="0.1">12 Awang DVC (1990) Canad. Pharmaceut. J. 123:121. </LTTextLineHorizontal><LTTextLineHorizontal y0="168.561" y1="177.714" x0="320.22" x1="478.21" width="157.99" height="9.153" bbox="[320.22, 168.561, 478.21, 177.714]" word_margin="0.1">13 Larson KM et al. (1984) J. Nat. Prod. 47:747. </LTTextLineHorizontal><LTTextLineHorizontal y0="157.221" y1="166.374" x0="320.22" x1="519.974" width="199.754" height="9.153" bbox="[320.22, 157.221, 519.974, 166.374]" word_margin="0.1">14 Janick J et al. (1989) Herbs, Spices &amp; Med. Plants 4:145. </LTTextLineHorizontal><LTTextLineHorizontal y0="145.941" y1="155.094" x0="320.22" x1="496.57" width="176.35" height="9.153" bbox="[320.22, 145.941, 496.57, 155.094]" word_margin="0.1">15 Alonso JR (1998) Tratado de Fitomedicina, p. 318. </LTTextLineHorizontal><LTTextLineHorizontal y0="134.601" y1="143.754" x0="320.22" x1="537.603" width="217.383" height="9.153" bbox="[320.22, 134.601, 537.603, 143.754]" word_margin="0.1">16 Cupp MJ (2000) Toxicology and Clinical Pharmacology, p. 161. </LTTextLineHorizontal><LTTextLineHorizontal y0="123.261" y1="132.414" x0="320.22" x1="469.512" width="149.292" height="9.153" bbox="[320.22, 123.261, 469.512, 132.414]" word_margin="0.1">17 Tyler VE (1993) The Honest Herbal, p. 51. </LTTextLineHorizontal><LTTextLineHorizontal y0="111.921" y1="121.074" x0="320.22" x1="524.062" width="203.842" height="9.153" bbox="[320.22, 111.921, 524.062, 121.074]" word_margin="0.1">18 McGuffin M et al. (1997) Botanical Safety Handbook, p. 20. </LTTextLineHorizontal><LTTextLineHorizontal y0="100.581" y1="109.734" x0="320.22" x1="528.251" width="208.031" height="9.153" bbox="[320.22, 100.581, 528.251, 109.734]" word_margin="0.1">19 Arteche A et al. (1998) Vadem&#233;cum de Prescripci&#243;n, p. 117. </LTTextLineHorizontal><LTTextLineHorizontal y0="89.036" y1="99.056" x0="320.22" x1="467.085" width="146.865" height="10.02" bbox="[320.22, 89.036, 467.085, 99.056]" word_margin="0.1">20 PDR for Herbal Medicines (2000), p. 114. </LTTextLineHorizontal><LTTextLineHorizontal y0="168.561" y1="177.561" x0="497.218" x1="499.27" width="2.052" height="9.0" bbox="[497.218, 168.561, 499.27, 177.561]" word_margin="0.1"> </LTTextLineHorizontal></LTTextBoxHorizontal>
    <LTTextLineHorizontal y0="31.176" y1="40.221" x0="297.48" x1="316.89" width="19.41" height="9.045" bbox="[297.48, 31.176, 316.89, 40.221]" word_margin="0.1"><LTTextBoxHorizontal y0="31.176" y1="40.221" x0="297.48" x1="316.89" width="19.41" height="9.045" bbox="[297.48, 31.176, 316.89, 40.221]" index="22">- 66 - </LTTextBoxHorizontal></LTTextLineHorizontal>
    <LTRect y0="747.84" y1="748.32" x0="69.42" x1="542.7" width="473.28" height="0.48" bbox="[69.42, 747.84, 542.7, 748.32]" linewidth="0" pts="[[69.42, 747.84], [542.7, 747.84], [542.7, 748.32], [69.42, 748.32]]"/>
    <LTRect y0="42.42" y1="42.9" x0="69.42" x1="542.7" width="473.28" height="0.48" bbox="[69.42, 42.42, 542.7, 42.9]" linewidth="0" pts="[[69.42, 42.42], [542.7, 42.42], [542.7, 42.9], [69.42, 42.9]]"/>
    <LTTextLineHorizontal y0="317.505" y1="328.487" x0="320.215" x1="468.085" width="147.87" height="10.982" bbox="[320.215, 317.505, 468.085, 328.487]" word_margin="0.1"> <LTRect y0="322.8" y1="323.46" x0="320.22" x1="464.22" width="144.0" height="0.66" bbox="[320.22, 322.8, 464.22, 323.46]" linewidth="0" pts="[[320.22, 322.8], [464.22, 322.8], [464.22, 323.46], [320.22, 323.46]]"/></LTTextLineHorizontal>
  </LTPage>
</pdfxml>
